{
  "id": 0,
  "name": "testGamemode",
  "inventory": [],
  "entities": [
    {
      "health": 60,
      "attack": 2,
      "visible": true,
      "currentDir": "NONE",
      "haveKey": false,
      "hasSunStone": false,
      "invincibleTickDuration": 0,
      "enemyAttack": true,
      "initialHealth": 60,
      "invincibleAmount": 0,
      "initialAttack": 2,
      "controlled": [],
      "traceList": [
        "NONE",
        "NONE",
        "NONE",
        "NONE",
        "NONE",
        "NONE",
        "NONE",
        "NONE"
      ],
      "position": {
        "x": 0,
        "y": 0,
        "layer": 0
      },
      "type": "player",
      "id": "0"
    },
    {
      "position": {
        "x": 1,
        "y": 0,
        "layer": 0
      },
      "type": "invincibility_potion",
      "id": "1"
    },
    {
      "tickrate": 15,
      "position": {
        "x": 2,
        "y": 2,
        "layer": 0
      },
      "type": "zombie_toast_spawner",
      "id": "2"
    }
  ],
  "gameMode": "hard",
  "goals": "",
  "historicalEntCount": 3,
  "tickNumber": 8,
  "spawnpoint": {
    "x": 0,
    "y": 0,
    "layer": 0
  },
  "foundGoals": {
    "goal": "",
    "hasCompleted": false
  },
  "goalConditions": "",
  "factory": {},
  "mercSpawnrate": 10,
  "spiderSpawnrate": 15,
  "rewindPath": "/rewind/1636858415454/"
}